qiskit_bip_mapper/__init__.py
qiskit_bip_mapper/bip_mapping.py
qiskit_bip_mapper/bip_model.py
qiskit_bip_mapper/plugin.py
qiskit_bip_mapper/tests/__init__.py
qiskit_bip_mapper/tests/test_bip_mapping.py
qiskit_bip_mapper/tests/test_plugin.py
qiskit_bip_mapper-0.1.0.dist-info/AUTHORS
qiskit_bip_mapper-0.1.0.dist-info/LICENSE.txt
qiskit_bip_mapper-0.1.0.dist-info/METADATA
qiskit_bip_mapper-0.1.0.dist-info/WHEEL
qiskit_bip_mapper-0.1.0.dist-info/entry_points.txt
qiskit_bip_mapper-0.1.0.dist-info/pbr.json
qiskit_bip_mapper-0.1.0.dist-info/top_level.txt
qiskit_bip_mapper-0.1.0.dist-info/RECORD
